kairo/__init__.py
kairo/cli.py
kairo/core.py
kairo/main.py
kairo/memory.py
kairo/retriever.py
kairo/utils.py
kairoai-1.0.0.dist-info/METADATA
kairoai-1.0.0.dist-info/WHEEL
kairoai-1.0.0.dist-info/entry_points.txt
kairoai-1.0.0.dist-info/top_level.txt
kairoai-1.0.0.dist-info/RECORD
