Metadata-Version: 2.4
Name: kairoAI
Version: 1.0.0
Requires-Python: >=3.8
Requires-Dist: openai
Requires-Dist: langchain
Requires-Dist: chromadb
Requires-Dist: rich
Requires-Dist: typer
Requires-Dist: pypdf
Requires-Dist: tiktoken
Dynamic: requires-dist
Dynamic: requires-python
